fireballpy/__init__.py
fireballpy/fireball.py
fireballpy/infodat.py
fireballpy/retro.py
fireballpy-0.0.1.dist-info/METADATA
fireballpy-0.0.1.dist-info/WHEEL
fireballpy-0.0.1.dist-info/licenses/LICENSE
fireballpy-0.0.1.dist-info/RECORD
